{"version":3,"kind":"Article","sha256":"640c8077e86d7b822b4168e2a46ea462ffad00dd209e2282abb2a08b45e7809a","slug":"index","location":"/index.md","dependencies":[],"frontmatter":{"title":"A Practical Guide to Running AI/ML Experiments on GCP","content_includes_title":false,"authors":[{"id":"AIMS TtT Team","name":"AIMS TtT Team"}],"license":{"content":{"id":"CC-BY-4.0","url":"https://creativecommons.org/licenses/by/4.0/","name":"Creative Commons Attribution 4.0 International","free":true,"CC":true}},"github":"https://github.com/rexsimiloluwa/aims-ai-gcp-tutorial","keywords":["GCP","AI","GPU","Machine Learning","Research","Experiments","MLOps"],"source_url":"https://github.com/rexsimiloluwa/aims-ai-gcp-tutorial/blob/main/index.md","edit_url":"https://github.com/rexsimiloluwa/aims-ai-gcp-tutorial/edit/main/index.md","exports":[{"format":"md","filename":"index.md","url":"/gcp-tutorial-aims/build/index-71d0a0c10af9ab0a3edce05638301c41.md"}]},"mdast":{"type":"root","children":[{"type":"block","children":[{"type":"paragraph","position":{"start":{"line":3,"column":1},"end":{"line":3,"column":1}},"children":[{"type":"text","value":"A hands-on tutorial for beginners who want to use Google Cloud Platform (GCP) for large-scale machine learning experiments or AI workloads.","position":{"start":{"line":3,"column":1},"end":{"line":3,"column":1}},"key":"yT4Skr0p2T"}],"key":"AQcHWT4E9O"},{"type":"heading","depth":2,"position":{"start":{"line":5,"column":1},"end":{"line":5,"column":1}},"children":[{"type":"text","value":"🎯 What You’ll Learn","position":{"start":{"line":5,"column":1},"end":{"line":5,"column":1}},"key":"zcb2JGdlkw"}],"identifier":"id-what-youll-learn","label":"🎯 What You’ll Learn","html_id":"id-what-youll-learn","implicit":true,"key":"qsyhgho3mC"},{"type":"list","ordered":false,"spread":false,"position":{"start":{"line":7,"column":1},"end":{"line":13,"column":1}},"children":[{"type":"listItem","spread":true,"position":{"start":{"line":7,"column":1},"end":{"line":7,"column":1}},"children":[{"type":"paragraph","children":[{"type":"text","value":"How to use the GCP console and the ","position":{"start":{"line":7,"column":1},"end":{"line":7,"column":1}},"key":"XbQsWnXTJk"},{"type":"inlineCode","value":"gcloud","position":{"start":{"line":7,"column":1},"end":{"line":7,"column":1}},"key":"ZX4hi1Ri7s"},{"type":"text","value":" CLI","position":{"start":{"line":7,"column":1},"end":{"line":7,"column":1}},"key":"ZtHICujktQ"}],"key":"l3DN8yMz12"}],"key":"qVCTavVIEA"},{"type":"listItem","spread":true,"position":{"start":{"line":8,"column":1},"end":{"line":8,"column":1}},"children":[{"type":"paragraph","children":[{"type":"text","value":"How to provision and manage virtual machines and GPU resources on GCP","position":{"start":{"line":8,"column":1},"end":{"line":8,"column":1}},"key":"ApG96lkhyr"}],"key":"Vdzo9vvurI"}],"key":"Em5IzVP7nW"},{"type":"listItem","spread":true,"position":{"start":{"line":9,"column":1},"end":{"line":9,"column":1}},"children":[{"type":"paragraph","children":[{"type":"text","value":"How to run large-scale ML experiments (like fine-tuning large language models) on GCP VMs","position":{"start":{"line":9,"column":1},"end":{"line":9,"column":1}},"key":"rwF1N7tcx9"}],"key":"zJuWZXmSPa"}],"key":"LR7R2gzfxD"},{"type":"listItem","spread":true,"position":{"start":{"line":10,"column":1},"end":{"line":10,"column":1}},"children":[{"type":"paragraph","children":[{"type":"text","value":"When to use virtual machines vs. managed services like Vertex AI","position":{"start":{"line":10,"column":1},"end":{"line":10,"column":1}},"key":"SjQsxdYdxA"}],"key":"xsrlseTPln"}],"key":"aeksP2EvCS"},{"type":"listItem","spread":true,"position":{"start":{"line":11,"column":1},"end":{"line":11,"column":1}},"children":[{"type":"paragraph","children":[{"type":"text","value":"How to predict and manage GPU memory","position":{"start":{"line":11,"column":1},"end":{"line":11,"column":1}},"key":"BOviq7gz8d"}],"key":"qVnZgKr9Ge"}],"key":"jAQHE7Ljds"},{"type":"listItem","spread":true,"position":{"start":{"line":12,"column":1},"end":{"line":13,"column":1}},"children":[{"type":"paragraph","children":[{"type":"text","value":"How to avoid expensive cloud mistakes with cost monitoring and budget alerts","position":{"start":{"line":12,"column":1},"end":{"line":12,"column":1}},"key":"l4nGDD5c9b"}],"key":"ZjQb3shSVI"}],"key":"DGF45LszAh"}],"key":"yH9134Cebd"},{"type":"heading","depth":2,"position":{"start":{"line":14,"column":1},"end":{"line":14,"column":1}},"children":[{"type":"text","value":"📋 Prerequisites","position":{"start":{"line":14,"column":1},"end":{"line":14,"column":1}},"key":"tfq2kBnOEx"}],"identifier":"id-prerequisites","label":"📋 Prerequisites","html_id":"id-prerequisites","implicit":true,"key":"x3h8oWvEpz"},{"type":"list","ordered":false,"spread":false,"position":{"start":{"line":16,"column":1},"end":{"line":28,"column":1}},"children":[{"type":"listItem","spread":true,"position":{"start":{"line":16,"column":1},"end":{"line":19,"column":1}},"children":[{"type":"paragraph","children":[{"type":"text","value":"Required:","position":{"start":{"line":16,"column":1},"end":{"line":16,"column":1}},"key":"i4RZBe7h3v"}],"key":"oq3H2rg7q0"},{"type":"list","ordered":false,"spread":false,"position":{"start":{"line":17,"column":1},"end":{"line":19,"column":1}},"children":[{"type":"listItem","spread":true,"position":{"start":{"line":17,"column":1},"end":{"line":17,"column":1}},"children":[{"type":"paragraph","children":[{"type":"text","value":"Python programming","position":{"start":{"line":17,"column":1},"end":{"line":17,"column":1}},"key":"JT8RhWUTwm"}],"key":"p68oUd930g"}],"key":"TiKJilnvyE"},{"type":"listItem","spread":true,"position":{"start":{"line":18,"column":1},"end":{"line":18,"column":1}},"children":[{"type":"paragraph","children":[{"type":"text","value":"Comfort with terminal/command line","position":{"start":{"line":18,"column":1},"end":{"line":18,"column":1}},"key":"UzzDx6Xcoh"}],"key":"Lfoiv2VsXs"}],"key":"GWdpRc7jsl"},{"type":"listItem","spread":true,"position":{"start":{"line":19,"column":1},"end":{"line":19,"column":1}},"children":[{"type":"paragraph","children":[{"type":"text","value":"Basic knowledge of machine learning/deep learning","position":{"start":{"line":19,"column":1},"end":{"line":19,"column":1}},"key":"szWR5oVs1J"}],"key":"Nfl3ZyfdnW"}],"key":"QcJNGcvLqp"}],"key":"gehloLKOmz"}],"key":"QkEhFP9PaN"},{"type":"listItem","spread":true,"position":{"start":{"line":20,"column":1},"end":{"line":23,"column":1}},"children":[{"type":"paragraph","children":[{"type":"text","value":"Not required:","position":{"start":{"line":20,"column":1},"end":{"line":20,"column":1}},"key":"YGEnM5GMSg"}],"key":"eZ8hHDTg8j"},{"type":"list","ordered":false,"spread":false,"position":{"start":{"line":21,"column":1},"end":{"line":23,"column":1}},"children":[{"type":"listItem","spread":true,"position":{"start":{"line":21,"column":1},"end":{"line":21,"column":1}},"children":[{"type":"paragraph","children":[{"type":"text","value":"GCP experience (we start from scratch!)","position":{"start":{"line":21,"column":1},"end":{"line":21,"column":1}},"key":"pgLahnzELf"}],"key":"tRI09JrFqx"}],"key":"LScF8maOOx"},{"type":"listItem","spread":true,"position":{"start":{"line":22,"column":1},"end":{"line":22,"column":1}},"children":[{"type":"paragraph","children":[{"type":"text","value":"Deep learning expertise","position":{"start":{"line":22,"column":1},"end":{"line":22,"column":1}},"key":"vRuqzPV3PE"}],"key":"lBFRpSoNyx"}],"key":"sEq3C8wbzF"},{"type":"listItem","spread":true,"position":{"start":{"line":23,"column":1},"end":{"line":23,"column":1}},"children":[{"type":"paragraph","children":[{"type":"text","value":"Cloud computing background","position":{"start":{"line":23,"column":1},"end":{"line":23,"column":1}},"key":"tIf0rTugmO"}],"key":"BRtxx1BYci"}],"key":"QUhOqEqcqv"}],"key":"usRSH7THSV"}],"key":"eP0zm0Akcj"},{"type":"listItem","spread":true,"position":{"start":{"line":24,"column":1},"end":{"line":28,"column":1}},"children":[{"type":"paragraph","children":[{"type":"text","value":"You will also need:","position":{"start":{"line":24,"column":1},"end":{"line":24,"column":1}},"key":"jhIvgTAjr9"}],"key":"MEYlOmFAxt"},{"type":"list","ordered":false,"spread":false,"position":{"start":{"line":25,"column":1},"end":{"line":28,"column":1}},"children":[{"type":"listItem","spread":true,"position":{"start":{"line":25,"column":1},"end":{"line":25,"column":1}},"children":[{"type":"paragraph","children":[{"type":"text","value":"A Google Cloud account (there is a free tier available with $300 credits)","position":{"start":{"line":25,"column":1},"end":{"line":25,"column":1}},"key":"dW2UNikq9u"}],"key":"ub7lMmMzhP"}],"key":"ibxgBubjCl"},{"type":"listItem","spread":true,"position":{"start":{"line":26,"column":1},"end":{"line":26,"column":1}},"children":[{"type":"paragraph","children":[{"type":"text","value":"A text editor (VS Code, Sublime Text, Cursor, etc.)","position":{"start":{"line":26,"column":1},"end":{"line":26,"column":1}},"key":"AHxV6jXdKD"}],"key":"BsANnzZ3rk"}],"key":"u59JwiNeWP"},{"type":"listItem","spread":true,"position":{"start":{"line":27,"column":1},"end":{"line":28,"column":1}},"children":[{"type":"paragraph","children":[{"type":"text","value":"Terminal access","position":{"start":{"line":27,"column":1},"end":{"line":27,"column":1}},"key":"HRgQBILCA9"}],"key":"xmc0s3O1WI"}],"key":"EhunQB5OGS"}],"key":"ZmVsVTdDiO"}],"key":"tPahdifujQ"}],"key":"KMAUQCtbeA"},{"type":"heading","depth":2,"position":{"start":{"line":29,"column":1},"end":{"line":29,"column":1}},"children":[{"type":"text","value":"🕥 Duration","position":{"start":{"line":29,"column":1},"end":{"line":29,"column":1}},"key":"pR8EN6pFM3"}],"identifier":"id-duration","label":"🕥 Duration","html_id":"id-duration","implicit":true,"key":"v2FwrUHyvJ"},{"type":"paragraph","position":{"start":{"line":31,"column":1},"end":{"line":31,"column":1}},"children":[{"type":"text","value":"4-6 hours (can be split into multiple sessions)","position":{"start":{"line":31,"column":1},"end":{"line":31,"column":1}},"key":"qA3QsRFiLw"}],"key":"RYrNBYL5LP"},{"type":"list","ordered":false,"spread":false,"position":{"start":{"line":33,"column":1},"end":{"line":35,"column":1}},"children":[{"type":"listItem","spread":true,"position":{"start":{"line":33,"column":1},"end":{"line":33,"column":1}},"children":[{"type":"paragraph","children":[{"type":"text","value":"Core tutorial: 3-4 hours","position":{"start":{"line":33,"column":1},"end":{"line":33,"column":1}},"key":"smD6wFIRRX"}],"key":"Pu3w3RZHtE"}],"key":"yJjRJuc8S6"},{"type":"listItem","spread":true,"position":{"start":{"line":34,"column":1},"end":{"line":35,"column":1}},"children":[{"type":"paragraph","children":[{"type":"text","value":"Optional appendices: 25-30 minutes additional","position":{"start":{"line":34,"column":1},"end":{"line":34,"column":1}},"key":"zjU1miYOJ3"}],"key":"EFdCE8zqx5"}],"key":"z6zAEolzYj"}],"key":"pLRKn7YxrG"},{"type":"heading","depth":2,"position":{"start":{"line":36,"column":1},"end":{"line":36,"column":1}},"children":[{"type":"text","value":"📚 Tutorial Structure","position":{"start":{"line":36,"column":1},"end":{"line":36,"column":1}},"key":"fWwTqln4Lw"}],"identifier":"id-tutorial-structure","label":"📚 Tutorial Structure","html_id":"id-tutorial-structure","implicit":true,"key":"e1gWuGU9X6"},{"type":"heading","depth":3,"position":{"start":{"line":38,"column":1},"end":{"line":38,"column":1}},"children":[{"type":"text","value":"Core Path","position":{"start":{"line":38,"column":1},"end":{"line":38,"column":1}},"key":"UbJBNGslje"}],"identifier":"core-path","label":"Core Path","html_id":"core-path","implicit":true,"key":"NCga6DZINk"},{"type":"table","position":{"start":{"line":40,"column":1},"end":{"line":45,"column":1}},"children":[{"type":"tableRow","position":{"start":{"line":40,"column":1},"end":{"line":40,"column":1}},"children":[{"type":"tableCell","header":true,"position":{"start":{"line":40,"column":1},"end":{"line":40,"column":1}},"children":[{"type":"text","value":"Part","position":{"start":{"line":40,"column":1},"end":{"line":40,"column":1}},"key":"VrOiXVjaGP"}],"key":"mihbE8Vceu"},{"type":"tableCell","header":true,"position":{"start":{"line":40,"column":1},"end":{"line":40,"column":1}},"children":[{"type":"text","value":"Title","position":{"start":{"line":40,"column":1},"end":{"line":40,"column":1}},"key":"BrZa5swKjM"}],"key":"nH3pmh0TeC"},{"type":"tableCell","header":true,"position":{"start":{"line":40,"column":1},"end":{"line":40,"column":1}},"children":[{"type":"text","value":"Time","position":{"start":{"line":40,"column":1},"end":{"line":40,"column":1}},"key":"CC8l1oJKyM"}],"key":"AqIbewnweE"},{"type":"tableCell","header":true,"position":{"start":{"line":40,"column":1},"end":{"line":40,"column":1}},"children":[{"type":"text","value":"Learning Objective","position":{"start":{"line":40,"column":1},"end":{"line":40,"column":1}},"key":"V32hQbkIh8"}],"key":"SGOsv9ZdLm"}],"key":"hdgQB219Vb"},{"type":"tableRow","position":{"start":{"line":42,"column":1},"end":{"line":42,"column":1}},"children":[{"type":"tableCell","position":{"start":{"line":42,"column":1},"end":{"line":42,"column":1}},"children":[{"type":"text","value":"1","position":{"start":{"line":42,"column":1},"end":{"line":42,"column":1}},"key":"VAzH49aT4h"}],"key":"SwyqZjXHWl"},{"type":"tableCell","position":{"start":{"line":42,"column":1},"end":{"line":42,"column":1}},"children":[{"type":"text","value":"GCP Foundations","position":{"start":{"line":42,"column":1},"end":{"line":42,"column":1}},"key":"zNPBMMtFsC"}],"key":"JL2lxz17xz"},{"type":"tableCell","position":{"start":{"line":42,"column":1},"end":{"line":42,"column":1}},"children":[{"type":"text","value":"30 mins","position":{"start":{"line":42,"column":1},"end":{"line":42,"column":1}},"key":"JQrYPkzyl0"}],"key":"h5eN9maTLw"},{"type":"tableCell","position":{"start":{"line":42,"column":1},"end":{"line":42,"column":1}},"children":[{"type":"text","value":"Understand GCP and interact with it via the console and ","position":{"start":{"line":42,"column":1},"end":{"line":42,"column":1}},"key":"Q3ydyP4Opm"},{"type":"inlineCode","value":"gcloud","position":{"start":{"line":42,"column":1},"end":{"line":42,"column":1}},"key":"UYMMvqD34X"},{"type":"text","value":" CLI","position":{"start":{"line":42,"column":1},"end":{"line":42,"column":1}},"key":"Ax9oUxu5Jy"}],"key":"p1S8J8sqIw"}],"key":"n9rPLwZqNZ"},{"type":"tableRow","position":{"start":{"line":43,"column":1},"end":{"line":43,"column":1}},"children":[{"type":"tableCell","position":{"start":{"line":43,"column":1},"end":{"line":43,"column":1}},"children":[{"type":"text","value":"2","position":{"start":{"line":43,"column":1},"end":{"line":43,"column":1}},"key":"Ok4Byzz4NK"}],"key":"gKLnnVM16I"},{"type":"tableCell","position":{"start":{"line":43,"column":1},"end":{"line":43,"column":1}},"children":[{"type":"text","value":"Running Experiments on GCP VMs","position":{"start":{"line":43,"column":1},"end":{"line":43,"column":1}},"key":"SwmkYvo5dj"}],"key":"hL4pMLkbQz"},{"type":"tableCell","position":{"start":{"line":43,"column":1},"end":{"line":43,"column":1}},"children":[{"type":"text","value":"45 mins","position":{"start":{"line":43,"column":1},"end":{"line":43,"column":1}},"key":"Ldk2cEA1Zc"}],"key":"mMBzuYi8mU"},{"type":"tableCell","position":{"start":{"line":43,"column":1},"end":{"line":43,"column":1}},"children":[{"type":"text","value":"Learn how to run AI/ML experiments on GCP virtual machines with GPU support","position":{"start":{"line":43,"column":1},"end":{"line":43,"column":1}},"key":"SwgxEXwsmd"}],"key":"PD4HOsWHSN"}],"key":"NDGXtTq34h"},{"type":"tableRow","position":{"start":{"line":44,"column":1},"end":{"line":44,"column":1}},"children":[{"type":"tableCell","position":{"start":{"line":44,"column":1},"end":{"line":44,"column":1}},"children":[{"type":"text","value":"3","position":{"start":{"line":44,"column":1},"end":{"line":44,"column":1}},"key":"ogm8MrQCYm"}],"key":"IzvxVmqDo5"},{"type":"tableCell","position":{"start":{"line":44,"column":1},"end":{"line":44,"column":1}},"children":[{"type":"text","value":"Vertex AI","position":{"start":{"line":44,"column":1},"end":{"line":44,"column":1}},"key":"X69poCG7No"}],"key":"pIwGyONpMr"},{"type":"tableCell","position":{"start":{"line":44,"column":1},"end":{"line":44,"column":1}},"children":[{"type":"text","value":"65 mins","position":{"start":{"line":44,"column":1},"end":{"line":44,"column":1}},"key":"EV79fGHSIp"}],"key":"UIwI0bIylg"},{"type":"tableCell","position":{"start":{"line":44,"column":1},"end":{"line":44,"column":1}},"children":[{"type":"text","value":"Understand how to use the managed Vertex AI service for training jobs and notebooks","position":{"start":{"line":44,"column":1},"end":{"line":44,"column":1}},"key":"ArFnuYk7Qw"}],"key":"kX8LqZJVwm"}],"key":"cRZs8L16Gq"},{"type":"tableRow","position":{"start":{"line":45,"column":1},"end":{"line":45,"column":1}},"children":[{"type":"tableCell","position":{"start":{"line":45,"column":1},"end":{"line":45,"column":1}},"children":[{"type":"text","value":"4","position":{"start":{"line":45,"column":1},"end":{"line":45,"column":1}},"key":"mNPIznE43s"}],"key":"c09Wwr1H13"},{"type":"tableCell","position":{"start":{"line":45,"column":1},"end":{"line":45,"column":1}},"children":[{"type":"text","value":"Cost Management","position":{"start":{"line":45,"column":1},"end":{"line":45,"column":1}},"key":"uzgqF5LZgb"}],"key":"MLQhkRkOsw"},{"type":"tableCell","position":{"start":{"line":45,"column":1},"end":{"line":45,"column":1}},"children":[{"type":"text","value":"30 mins","position":{"start":{"line":45,"column":1},"end":{"line":45,"column":1}},"key":"Ma8lcxyGzn"}],"key":"VO2mz5SWRm"},{"type":"tableCell","position":{"start":{"line":45,"column":1},"end":{"line":45,"column":1}},"children":[{"type":"text","value":"Understand budget alerts and best practices for cost management","position":{"start":{"line":45,"column":1},"end":{"line":45,"column":1}},"key":"j6b1pKuu9Y"}],"key":"wCFy9rbzFg"}],"key":"NYw5EQ3GMd"}],"key":"qDqBz3dVfx"},{"type":"heading","depth":3,"position":{"start":{"line":47,"column":1},"end":{"line":47,"column":1}},"children":[{"type":"text","value":"Appendix (Optional)","position":{"start":{"line":47,"column":1},"end":{"line":47,"column":1}},"key":"aM2Srzwn8H"}],"identifier":"appendix-optional","label":"Appendix (Optional)","html_id":"appendix-optional","implicit":true,"key":"R5TyGEEbq7"},{"type":"table","position":{"start":{"line":49,"column":1},"end":{"line":51,"column":1}},"children":[{"type":"tableRow","position":{"start":{"line":49,"column":1},"end":{"line":49,"column":1}},"children":[{"type":"tableCell","header":true,"position":{"start":{"line":49,"column":1},"end":{"line":49,"column":1}},"children":[{"type":"text","value":"Appendix","position":{"start":{"line":49,"column":1},"end":{"line":49,"column":1}},"key":"mzo1VFAkgP"}],"key":"oX7DwTgZiq"},{"type":"tableCell","header":true,"position":{"start":{"line":49,"column":1},"end":{"line":49,"column":1}},"children":[{"type":"text","value":"Title","position":{"start":{"line":49,"column":1},"end":{"line":49,"column":1}},"key":"DAiiufyffY"}],"key":"mwTs5y9VbN"},{"type":"tableCell","header":true,"position":{"start":{"line":49,"column":1},"end":{"line":49,"column":1}},"children":[{"type":"text","value":"Time","position":{"start":{"line":49,"column":1},"end":{"line":49,"column":1}},"key":"UKVZG8SEWl"}],"key":"FN6GmmVRCr"},{"type":"tableCell","header":true,"position":{"start":{"line":49,"column":1},"end":{"line":49,"column":1}},"children":[{"type":"text","value":"Focus","position":{"start":{"line":49,"column":1},"end":{"line":49,"column":1}},"key":"RjH2wbkcvh"}],"key":"lv4Q4Mjnod"}],"key":"PeVgCsOKBw"},{"type":"tableRow","position":{"start":{"line":51,"column":1},"end":{"line":51,"column":1}},"children":[{"type":"tableCell","position":{"start":{"line":51,"column":1},"end":{"line":51,"column":1}},"children":[{"type":"text","value":"A","position":{"start":{"line":51,"column":1},"end":{"line":51,"column":1}},"key":"B4aNhqWi1R"}],"key":"v8AjeTkT50"},{"type":"tableCell","position":{"start":{"line":51,"column":1},"end":{"line":51,"column":1}},"children":[{"type":"text","value":"GPU Memory Maths","position":{"start":{"line":51,"column":1},"end":{"line":51,"column":1}},"key":"oP9zB5dTGt"}],"key":"slfPfs9hLd"},{"type":"tableCell","position":{"start":{"line":51,"column":1},"end":{"line":51,"column":1}},"children":[{"type":"text","value":"45 mins","position":{"start":{"line":51,"column":1},"end":{"line":51,"column":1}},"key":"uMmzRpeBkA"}],"key":"OuwuOZrwCF"},{"type":"tableCell","position":{"start":{"line":51,"column":1},"end":{"line":51,"column":1}},"children":[{"type":"text","value":"Understand how to estimate GPU memory requirements, avoid OOM errors, and choose the right GPU for your needs","position":{"start":{"line":51,"column":1},"end":{"line":51,"column":1}},"key":"FNXEgxhZcW"}],"key":"tHLHRrJb5q"}],"key":"dGkBOOWg7p"}],"key":"AAIwSmUJzz"},{"type":"heading","depth":2,"position":{"start":{"line":53,"column":1},"end":{"line":53,"column":1}},"children":[{"type":"text","value":"💡 What Makes This Tutorial Different","position":{"start":{"line":53,"column":1},"end":{"line":53,"column":1}},"key":"h3EMpoFxml"}],"identifier":"id-what-makes-this-tutorial-different","label":"💡 What Makes This Tutorial Different","html_id":"id-what-makes-this-tutorial-different","implicit":true,"key":"YTwiLbcoor"},{"type":"paragraph","position":{"start":{"line":55,"column":1},"end":{"line":55,"column":1}},"children":[{"type":"text","value":"This tutorial teaches you what you need to run AI/ML experiments on GCP, emphasizing:","position":{"start":{"line":55,"column":1},"end":{"line":55,"column":1}},"key":"oKJZrjHX7W"}],"key":"Rn4MmiOFGH"},{"type":"list","ordered":false,"spread":false,"position":{"start":{"line":57,"column":1},"end":{"line":61,"column":1}},"children":[{"type":"listItem","spread":true,"position":{"start":{"line":57,"column":1},"end":{"line":57,"column":1}},"children":[{"type":"paragraph","children":[{"type":"text","value":"Systems thinking for ML infrastructure","position":{"start":{"line":57,"column":1},"end":{"line":57,"column":1}},"key":"OiLhbrVgpv"}],"key":"FTFHPYoXV5"}],"key":"i49TIs508v"},{"type":"listItem","spread":true,"position":{"start":{"line":58,"column":1},"end":{"line":58,"column":1}},"children":[{"type":"paragraph","children":[{"type":"text","value":"Cost-conscious cloud practices","position":{"start":{"line":58,"column":1},"end":{"line":58,"column":1}},"key":"P2ZRlqi2pY"}],"key":"IE4nkE6bF4"}],"key":"veNM0SS4NK"},{"type":"listItem","spread":true,"position":{"start":{"line":59,"column":1},"end":{"line":59,"column":1}},"children":[{"type":"paragraph","children":[{"type":"text","value":"How to structure reproducible AI/ML experiments for real-world projects","position":{"start":{"line":59,"column":1},"end":{"line":59,"column":1}},"key":"E2tlV6N2ya"}],"key":"uwjcx5d07c"}],"key":"hzrPVAiGc2"},{"type":"listItem","spread":true,"position":{"start":{"line":60,"column":1},"end":{"line":61,"column":1}},"children":[{"type":"paragraph","children":[{"type":"text","value":"Hands-on practice with every learned concept","position":{"start":{"line":60,"column":1},"end":{"line":60,"column":1}},"key":"RqyexguTA1"}],"key":"YuGwzKMLgE"}],"key":"SXTOwWQ60y"}],"key":"UOiZovQBdN"},{"type":"paragraph","position":{"start":{"line":62,"column":1},"end":{"line":62,"column":1}},"children":[{"type":"text","value":"The content is also structured to be used on-demand so you do not have to read the entire tutorial.","position":{"start":{"line":62,"column":1},"end":{"line":62,"column":1}},"key":"zOqtpsFopo"}],"key":"BrVUEwdiIL"},{"type":"heading","depth":2,"position":{"start":{"line":64,"column":1},"end":{"line":64,"column":1}},"children":[{"type":"text","value":"🎓 Who This is For","position":{"start":{"line":64,"column":1},"end":{"line":64,"column":1}},"key":"YOOgEQVOFb"}],"identifier":"id-who-this-is-for","label":"🎓 Who This is For","html_id":"id-who-this-is-for","implicit":true,"key":"BHVhg5A1M1"},{"type":"paragraph","position":{"start":{"line":66,"column":1},"end":{"line":66,"column":1}},"children":[{"type":"text","value":"This tutorial was particularly designed for ","position":{"start":{"line":66,"column":1},"end":{"line":66,"column":1}},"key":"LP7rpw5SOp"},{"type":"strong","position":{"start":{"line":66,"column":1},"end":{"line":66,"column":1}},"children":[{"type":"text","value":"AIMS AI for Science students","position":{"start":{"line":66,"column":1},"end":{"line":66,"column":1}},"key":"Ho6BgxCRHN"}],"key":"hDCizGJgTE"},{"type":"text","value":" who do not have a background in cloud computing or software engineering, helping them use GCP more effectively for their research projects.","position":{"start":{"line":66,"column":1},"end":{"line":66,"column":1}},"key":"bEINil8kgk"}],"key":"wCksU7a5nO"},{"type":"paragraph","position":{"start":{"line":68,"column":1},"end":{"line":68,"column":1}},"children":[{"type":"text","value":"However, it should be generally helpful for:","position":{"start":{"line":68,"column":1},"end":{"line":68,"column":1}},"key":"zUElHylNin"}],"key":"RufZPQlaA3"},{"type":"list","ordered":false,"spread":false,"position":{"start":{"line":70,"column":1},"end":{"line":72,"column":1}},"children":[{"type":"listItem","spread":true,"position":{"start":{"line":70,"column":1},"end":{"line":70,"column":1}},"children":[{"type":"paragraph","children":[{"type":"text","value":"Beginner AI/ML students and researchers","position":{"start":{"line":70,"column":1},"end":{"line":70,"column":1}},"key":"nOJ8gpYgPA"}],"key":"MyrEDplZHo"}],"key":"JSTcw7xBeE"},{"type":"listItem","spread":true,"position":{"start":{"line":71,"column":1},"end":{"line":72,"column":1}},"children":[{"type":"paragraph","children":[{"type":"text","value":"Anyone curious about using GCP for running AI/ML experiments","position":{"start":{"line":71,"column":1},"end":{"line":71,"column":1}},"key":"u398KEXgf1"}],"key":"eQRExAVZ2W"}],"key":"cJYtdkji1u"}],"key":"UHMTvfVjAl"},{"type":"heading","depth":2,"position":{"start":{"line":73,"column":1},"end":{"line":73,"column":1}},"children":[{"type":"text","value":"🧠 How to Use This Tutorial","position":{"start":{"line":73,"column":1},"end":{"line":73,"column":1}},"key":"Kr9j9Oh2rD"}],"identifier":"id-how-to-use-this-tutorial","label":"🧠 How to Use This Tutorial","html_id":"id-how-to-use-this-tutorial","implicit":true,"key":"GNJM5H7MPn"},{"type":"heading","depth":3,"position":{"start":{"line":75,"column":1},"end":{"line":75,"column":1}},"children":[{"type":"text","value":"Option 1: Linear (Recommended for beginners)","position":{"start":{"line":75,"column":1},"end":{"line":75,"column":1}},"key":"CH7Se8U0Xe"}],"identifier":"option-1-linear-recommended-for-beginners","label":"Option 1: Linear (Recommended for beginners)","html_id":"option-1-linear-recommended-for-beginners","implicit":true,"key":"EeRExPaHsi"},{"type":"paragraph","position":{"start":{"line":77,"column":1},"end":{"line":77,"column":1}},"children":[{"type":"text","value":"Start from Part 1 and work through sequentially.","position":{"start":{"line":77,"column":1},"end":{"line":77,"column":1}},"key":"gxPs0nN7m6"}],"key":"cHtjMQPFgq"},{"type":"heading","depth":3,"position":{"start":{"line":79,"column":1},"end":{"line":79,"column":1}},"children":[{"type":"text","value":"Option 2: Jump to What You Need","position":{"start":{"line":79,"column":1},"end":{"line":79,"column":1}},"key":"AqWOi3zIJu"}],"identifier":"option-2-jump-to-what-you-need","label":"Option 2: Jump to What You Need","html_id":"option-2-jump-to-what-you-need","implicit":true,"key":"zePXa0JGkR"},{"type":"list","ordered":false,"spread":false,"position":{"start":{"line":81,"column":1},"end":{"line":86,"column":1}},"children":[{"type":"listItem","spread":true,"position":{"start":{"line":81,"column":1},"end":{"line":81,"column":1}},"children":[{"type":"paragraph","children":[{"type":"text","value":"Need a quick-start guide to using GCP? → ","position":{"start":{"line":81,"column":1},"end":{"line":81,"column":1}},"key":"ZHqggMtjZY"},{"type":"strong","position":{"start":{"line":81,"column":1},"end":{"line":81,"column":1}},"children":[{"type":"link","url":"/part1-gcp-foundations","position":{"start":{"line":81,"column":1},"end":{"line":81,"column":1}},"children":[{"type":"text","value":"Part 1","position":{"start":{"line":81,"column":1},"end":{"line":81,"column":1}},"key":"lqgROqeZKv"}],"urlSource":"/part1-gcp-foundations","key":"h0mQNO4dql"}],"key":"t2HtjtYbze"}],"key":"La6jB3QZlN"}],"key":"lbV6auaZkh"},{"type":"listItem","spread":true,"position":{"start":{"line":82,"column":1},"end":{"line":82,"column":1}},"children":[{"type":"paragraph","children":[{"type":"text","value":"Want to run ML experiments on a GPU VM? → ","position":{"start":{"line":82,"column":1},"end":{"line":82,"column":1}},"key":"NQweqPt8wm"},{"type":"strong","position":{"start":{"line":82,"column":1},"end":{"line":82,"column":1}},"children":[{"type":"link","url":"/part2-running-experiments-on-gcp-vms","position":{"start":{"line":82,"column":1},"end":{"line":82,"column":1}},"children":[{"type":"text","value":"Part 2","position":{"start":{"line":82,"column":1},"end":{"line":82,"column":1}},"key":"xQMM6GeAso"}],"urlSource":"/part2-running-experiments-on-gcp-vms","key":"jrvBSMkWOR"}],"key":"O7ixOWAzdk"}],"key":"fZNuoO4kRA"}],"key":"cQKg1MAs5m"},{"type":"listItem","spread":true,"position":{"start":{"line":83,"column":1},"end":{"line":83,"column":1}},"children":[{"type":"paragraph","children":[{"type":"text","value":"Want to learn how to use managed services like Vertex AI? → ","position":{"start":{"line":83,"column":1},"end":{"line":83,"column":1}},"key":"L2WjNPUvxO"},{"type":"strong","position":{"start":{"line":83,"column":1},"end":{"line":83,"column":1}},"children":[{"type":"link","url":"/part3-vertex-ai","position":{"start":{"line":83,"column":1},"end":{"line":83,"column":1}},"children":[{"type":"text","value":"Part 3","position":{"start":{"line":83,"column":1},"end":{"line":83,"column":1}},"key":"pEU13uPqrY"}],"urlSource":"/part3-vertex-ai","key":"VLUd26ajMr"}],"key":"h2cEiZ3zCU"}],"key":"B4Y5fjRzXx"}],"key":"rDhx3dDauu"},{"type":"listItem","spread":true,"position":{"start":{"line":84,"column":1},"end":{"line":84,"column":1}},"children":[{"type":"paragraph","children":[{"type":"text","value":"Need to understand how to monitor costs to manage your GCP credits properly? → ","position":{"start":{"line":84,"column":1},"end":{"line":84,"column":1}},"key":"Bts8x1d4SA"},{"type":"strong","position":{"start":{"line":84,"column":1},"end":{"line":84,"column":1}},"children":[{"type":"link","url":"/part4-cost-management","position":{"start":{"line":84,"column":1},"end":{"line":84,"column":1}},"children":[{"type":"text","value":"Part 4","position":{"start":{"line":84,"column":1},"end":{"line":84,"column":1}},"key":"uTea9Luor3"}],"urlSource":"/part4-cost-management","key":"SW3J2C6AjC"}],"key":"WoqGDqMraq"}],"key":"ApoxLGE7o7"}],"key":"GJyEWyacdE"},{"type":"listItem","spread":true,"position":{"start":{"line":85,"column":1},"end":{"line":86,"column":1}},"children":[{"type":"paragraph","children":[{"type":"text","value":"Need to know how to choose a GPU for your experiment? → ","position":{"start":{"line":85,"column":1},"end":{"line":85,"column":1}},"key":"kC3hh00V1H"},{"type":"strong","position":{"start":{"line":85,"column":1},"end":{"line":85,"column":1}},"children":[{"type":"link","url":"/appendix","position":{"start":{"line":85,"column":1},"end":{"line":85,"column":1}},"children":[{"type":"text","value":"Appendix A","position":{"start":{"line":85,"column":1},"end":{"line":85,"column":1}},"key":"NTXl1uRBG5"}],"urlSource":"/appendix","key":"FjKMLPPaYg"}],"key":"YV52GQTAOg"}],"key":"sqznrKOkD3"}],"key":"hwARCusebB"}],"key":"F25vq6wpNo"},{"type":"heading","depth":2,"position":{"start":{"line":87,"column":1},"end":{"line":87,"column":1}},"children":[{"type":"text","value":"🫱🏿‍🫲🏾 Contributing","position":{"start":{"line":87,"column":1},"end":{"line":87,"column":1}},"key":"HsHd4pCmbF"}],"identifier":"id-contributing","label":"🫱🏿‍🫲🏾 Contributing","html_id":"id-contributing","implicit":true,"key":"GBRBuJ6E13"},{"type":"paragraph","position":{"start":{"line":89,"column":1},"end":{"line":89,"column":1}},"children":[{"type":"text","value":"This tutorial is fully ","position":{"start":{"line":89,"column":1},"end":{"line":89,"column":1}},"key":"zgobc3IS4J"},{"type":"strong","position":{"start":{"line":89,"column":1},"end":{"line":89,"column":1}},"children":[{"type":"text","value":"open-source","position":{"start":{"line":89,"column":1},"end":{"line":89,"column":1}},"key":"gbCyev50dB"}],"key":"oKR0FzmyvI"},{"type":"text","value":"! We welcome:","position":{"start":{"line":89,"column":1},"end":{"line":89,"column":1}},"key":"NTubvDiOjM"}],"key":"UkytGiN6hc"},{"type":"list","ordered":false,"spread":false,"position":{"start":{"line":91,"column":1},"end":{"line":95,"column":1}},"children":[{"type":"listItem","spread":true,"position":{"start":{"line":91,"column":1},"end":{"line":91,"column":1}},"children":[{"type":"paragraph","children":[{"type":"text","value":"🐛 Bug reports","position":{"start":{"line":91,"column":1},"end":{"line":91,"column":1}},"key":"pnIwytoerz"}],"key":"nbRRnbx9x2"}],"key":"XDWP4WzpfV"},{"type":"listItem","spread":true,"position":{"start":{"line":92,"column":1},"end":{"line":92,"column":1}},"children":[{"type":"paragraph","children":[{"type":"text","value":"💡 Suggestions for improvements","position":{"start":{"line":92,"column":1},"end":{"line":92,"column":1}},"key":"uJEHJGO9Gw"}],"key":"OC7Pxr73dg"}],"key":"WLr0VmjBUa"},{"type":"listItem","spread":true,"position":{"start":{"line":93,"column":1},"end":{"line":93,"column":1}},"children":[{"type":"paragraph","children":[{"type":"text","value":"📝 Additional sections, examples, or exercises","position":{"start":{"line":93,"column":1},"end":{"line":93,"column":1}},"key":"Im1RC4d9Ec"}],"key":"znETxnRppQ"}],"key":"eyFYByx6ne"},{"type":"listItem","spread":true,"position":{"start":{"line":94,"column":1},"end":{"line":95,"column":1}},"children":[{"type":"paragraph","children":[{"type":"text","value":"🌎 Translations","position":{"start":{"line":94,"column":1},"end":{"line":94,"column":1}},"key":"LNxHuRIdQF"}],"key":"zJOj10LrZ8"}],"key":"xYkEoflcM7"}],"key":"bHhqdMVCPc"},{"type":"paragraph","position":{"start":{"line":96,"column":1},"end":{"line":96,"column":1}},"children":[{"type":"text","value":"See ","position":{"start":{"line":96,"column":1},"end":{"line":96,"column":1}},"key":"GOOOnQZnQS"},{"type":"link","url":"/gcp-tutorial-aims/build/CONTRIBUTING-532ef9d3fc6d01034580937695091f3c.md","position":{"start":{"line":96,"column":1},"end":{"line":96,"column":1}},"children":[{"type":"text","value":"CONTRIBUTING.md","position":{"start":{"line":96,"column":1},"end":{"line":96,"column":1}},"key":"RIUDQjwsCr"}],"urlSource":"./CONTRIBUTING.md","static":true,"protocol":"file","key":"uIQ1cPkagK"},{"type":"text","value":" for details.","position":{"start":{"line":96,"column":1},"end":{"line":96,"column":1}},"key":"Lzx2UQD3Fb"}],"key":"x6Sl0MFXMz"},{"type":"heading","depth":2,"position":{"start":{"line":98,"column":1},"end":{"line":98,"column":1}},"children":[{"type":"text","value":"📄 License","position":{"start":{"line":98,"column":1},"end":{"line":98,"column":1}},"key":"vSjFNYDfo0"}],"identifier":"id-license","label":"📄 License","html_id":"id-license","implicit":true,"key":"OvgYjccisO"},{"type":"paragraph","position":{"start":{"line":100,"column":1},"end":{"line":100,"column":1}},"children":[{"type":"text","value":"This tutorial is released under the CC-BY-4.0 License. See ","position":{"start":{"line":100,"column":1},"end":{"line":100,"column":1}},"key":"rElGyxJc4Q"},{"type":"inlineCode","value":"LICENSE","position":{"start":{"line":100,"column":1},"end":{"line":100,"column":1}},"key":"GWkmbFJirX"},{"type":"text","value":" for details.","position":{"start":{"line":100,"column":1},"end":{"line":100,"column":1}},"key":"jLuVnLyr2S"}],"key":"z7gMLusxIG"},{"type":"thematicBreak","position":{"start":{"line":102,"column":1},"end":{"line":102,"column":1}},"key":"ZdB1FtPeqt"},{"type":"paragraph","position":{"start":{"line":104,"column":1},"end":{"line":104,"column":1}},"children":[{"type":"strong","position":{"start":{"line":104,"column":1},"end":{"line":104,"column":1}},"children":[{"type":"text","value":"Let’s get started!","position":{"start":{"line":104,"column":1},"end":{"line":104,"column":1}},"key":"Dn6DohW6Ct"}],"key":"hGTRHOdelb"},{"type":"text","value":" → ","position":{"start":{"line":104,"column":1},"end":{"line":104,"column":1}},"key":"OizPIhh4sK"},{"type":"link","url":"/part1-gcp-foundations","position":{"start":{"line":104,"column":1},"end":{"line":104,"column":1}},"children":[{"type":"text","value":"Part 1: GCP Foundations","position":{"start":{"line":104,"column":1},"end":{"line":104,"column":1}},"key":"ZZgowfkFrE"}],"urlSource":"part1-gcp-foundations/index.md","dataUrl":"/part1-gcp-foundations.index.json","internal":true,"protocol":"file","key":"r9GrJXCkGF"}],"key":"oixM3P3YfF"}],"key":"k3xSR1g1fv"}],"key":"XTbP9tkFpo"},"references":{"cite":{"order":[],"data":{}}},"footer":{"navigation":{"next":{"title":"Introduction","url":"/part1-gcp-foundations","group":"Part 1 - GCP Foundations"}}},"domain":"http://localhost:3000"}