{"version":3,"kind":"Article","sha256":"df7762bb39f8296c43c0531a7a13c7fe704ca79469d79ebe646b10914f9c84f8","slug":"part1-gcp-foundations.the-gcloud-cli","location":"/part1-gcp-foundations/03-the-gcloud-cli.md","dependencies":[],"frontmatter":{"title":"The Google Cloud CLI (gcloud)","content_includes_title":false,"authors":[{"id":"AIMS TtT Team","name":"AIMS TtT Team"}],"license":{"content":{"id":"CC-BY-4.0","url":"https://creativecommons.org/licenses/by/4.0/","name":"Creative Commons Attribution 4.0 International","free":true,"CC":true}},"github":"https://github.com/rexsimiloluwa/aims-ai-gcp-tutorial","keywords":["GCP","AI","GPU","Machine Learning","Research","Experiments","MLOps"],"numbering":{"title":{"offset":1}},"source_url":"https://github.com/rexsimiloluwa/aims-ai-gcp-tutorial/blob/main/part1-gcp-foundations/03-the-gcloud-cli.md","edit_url":"https://github.com/rexsimiloluwa/aims-ai-gcp-tutorial/edit/main/part1-gcp-foundations/03-the-gcloud-cli.md","exports":[{"format":"md","filename":"03-the-gcloud-cli.md","url":"/build/03-the-gcloud-cli-f9258610bca718ac179d295d96c927cf.md"}]},"mdast":{"type":"root","children":[{"type":"block","children":[{"type":"paragraph","position":{"start":{"line":3,"column":1},"end":{"line":3,"column":1}},"children":[{"type":"text","value":"While the GCP Console is great for interacting with GCP through a graphical interface, the ","position":{"start":{"line":3,"column":1},"end":{"line":3,"column":1}},"key":"vKWW0FqaTh"},{"type":"inlineCode","value":"gcloud","position":{"start":{"line":3,"column":1},"end":{"line":3,"column":1}},"key":"jejXXGFFQ4"},{"type":"text","value":" CLI (Command Line Interface) is the primary tool for automating tasks and managing resources from your terminal.","position":{"start":{"line":3,"column":1},"end":{"line":3,"column":1}},"key":"SFLKfqNF5W"}],"key":"MEPv0QmETQ"},{"type":"paragraph","position":{"start":{"line":5,"column":1},"end":{"line":5,"column":1}},"children":[{"type":"text","value":"In a nutshell, it allows you to interact with GCP services through text commands instead of clicking through the web interface. The ","position":{"start":{"line":5,"column":1},"end":{"line":5,"column":1}},"key":"h5Bo4FaGvu"},{"type":"inlineCode","value":"gcloud","position":{"start":{"line":5,"column":1},"end":{"line":5,"column":1}},"key":"N18nY0yIjk"},{"type":"text","value":" CLI is also part of the ","position":{"start":{"line":5,"column":1},"end":{"line":5,"column":1}},"key":"mxKTKiplqH"},{"type":"strong","position":{"start":{"line":5,"column":1},"end":{"line":5,"column":1}},"children":[{"type":"text","value":"Google Cloud SDK","position":{"start":{"line":5,"column":1},"end":{"line":5,"column":1}},"key":"YwtfGVMCh2"}],"key":"ui70lIowAg"},{"type":"text","value":".","position":{"start":{"line":5,"column":1},"end":{"line":5,"column":1}},"key":"nTY9SERa37"}],"key":"fgwnehV6zj"},{"type":"heading","depth":2,"position":{"start":{"line":7,"column":1},"end":{"line":7,"column":1}},"children":[{"type":"text","value":"Why Use the CLI?","position":{"start":{"line":7,"column":1},"end":{"line":7,"column":1}},"key":"xJ36izzPyS"}],"identifier":"why-use-the-cli","label":"Why Use the CLI?","html_id":"why-use-the-cli","implicit":true,"key":"WGcQGZ1GBl"},{"type":"list","ordered":false,"spread":false,"position":{"start":{"line":9,"column":1},"end":{"line":12,"column":1}},"children":[{"type":"listItem","spread":true,"position":{"start":{"line":9,"column":1},"end":{"line":9,"column":1}},"children":[{"type":"paragraph","children":[{"type":"strong","position":{"start":{"line":9,"column":1},"end":{"line":9,"column":1}},"children":[{"type":"text","value":"Speed:","position":{"start":{"line":9,"column":1},"end":{"line":9,"column":1}},"key":"euQiQyuad0"}],"key":"Gq7ZIwlYPW"},{"type":"text","value":" Perform complex tasks with a single command rather than clicking through multiple menus.","position":{"start":{"line":9,"column":1},"end":{"line":9,"column":1}},"key":"DS0tyBVMWR"}],"key":"HMP5Rt3O1z"}],"key":"dKy5Xx9xgw"},{"type":"listItem","spread":true,"position":{"start":{"line":10,"column":1},"end":{"line":10,"column":1}},"children":[{"type":"paragraph","children":[{"type":"strong","position":{"start":{"line":10,"column":1},"end":{"line":10,"column":1}},"children":[{"type":"text","value":"Automation:","position":{"start":{"line":10,"column":1},"end":{"line":10,"column":1}},"key":"sMLpRRvmpF"}],"key":"V5Apr8xZpx"},{"type":"text","value":" Write scripts to automate repetitive tasks like deploying dozens of virtual machines or storage buckets at once with scripts instead of manual clicking.","position":{"start":{"line":10,"column":1},"end":{"line":10,"column":1}},"key":"sjiC5xGbZZ"}],"key":"ZkAFXNDkK7"}],"key":"jVLCSeLYBG"},{"type":"listItem","spread":true,"position":{"start":{"line":11,"column":1},"end":{"line":12,"column":1}},"children":[{"type":"paragraph","children":[{"type":"strong","position":{"start":{"line":11,"column":1},"end":{"line":11,"column":1}},"children":[{"type":"text","value":"Consistency:","position":{"start":{"line":11,"column":1},"end":{"line":11,"column":1}},"key":"r9I077WHiq"}],"key":"DdACXpouoG"},{"type":"text","value":" Ensure that resources are created with the exact same configurations every time.","position":{"start":{"line":11,"column":1},"end":{"line":11,"column":1}},"key":"Wo32DpIAUM"}],"key":"kG3P1oPncs"}],"key":"VlCEoOjuGq"}],"key":"hcAbdBaHjc"},{"type":"heading","depth":2,"position":{"start":{"line":13,"column":1},"end":{"line":13,"column":1}},"children":[{"type":"text","value":"When To Use the CLI?","position":{"start":{"line":13,"column":1},"end":{"line":13,"column":1}},"key":"zBUQnShqKq"}],"identifier":"when-to-use-the-cli","label":"When To Use the CLI?","html_id":"when-to-use-the-cli","implicit":true,"key":"xRC4gyuHBP"},{"type":"list","ordered":false,"spread":false,"position":{"start":{"line":15,"column":1},"end":{"line":20,"column":1}},"children":[{"type":"listItem","spread":true,"position":{"start":{"line":15,"column":1},"end":{"line":15,"column":1}},"children":[{"type":"paragraph","children":[{"type":"text","value":"✅ ","position":{"start":{"line":15,"column":1},"end":{"line":15,"column":1}},"key":"VrPH6bS98t"},{"type":"strong","position":{"start":{"line":15,"column":1},"end":{"line":15,"column":1}},"children":[{"type":"text","value":"Automation and scripting:","position":{"start":{"line":15,"column":1},"end":{"line":15,"column":1}},"key":"VFPymsNuxn"}],"key":"z8Uyykuro3"},{"type":"text","value":" Perfect for repetitive tasks that you don’t want to do by hand.","position":{"start":{"line":15,"column":1},"end":{"line":15,"column":1}},"key":"aW2m97rwHh"}],"key":"m7BXz2D0vs"}],"key":"cQad8sGcTc"},{"type":"listItem","spread":true,"position":{"start":{"line":16,"column":1},"end":{"line":16,"column":1}},"children":[{"type":"paragraph","children":[{"type":"text","value":"✅ ","position":{"start":{"line":16,"column":1},"end":{"line":16,"column":1}},"key":"LyVqq4QEBF"},{"type":"strong","position":{"start":{"line":16,"column":1},"end":{"line":16,"column":1}},"children":[{"type":"text","value":"Reproducible infrastructure setups:","position":{"start":{"line":16,"column":1},"end":{"line":16,"column":1}},"key":"IsTYjFWaIi"}],"key":"KzpoqHodlv"},{"type":"text","value":" Ensure your environment is the same every time you deploy.","position":{"start":{"line":16,"column":1},"end":{"line":16,"column":1}},"key":"zGEXfxs4t2"}],"key":"MTXurPJRQg"}],"key":"fqmkiqyP4f"},{"type":"listItem","spread":true,"position":{"start":{"line":17,"column":1},"end":{"line":17,"column":1}},"children":[{"type":"paragraph","children":[{"type":"text","value":"✅ ","position":{"start":{"line":17,"column":1},"end":{"line":17,"column":1}},"key":"fDKIHFzG1R"},{"type":"strong","position":{"start":{"line":17,"column":1},"end":{"line":17,"column":1}},"children":[{"type":"text","value":"Batch operations:","position":{"start":{"line":17,"column":1},"end":{"line":17,"column":1}},"key":"q6pSgKRhO6"}],"key":"EPdivZgGvL"},{"type":"text","value":" Manage multiple resources (like 50 VMs) with a single command.","position":{"start":{"line":17,"column":1},"end":{"line":17,"column":1}},"key":"LtS2zVrgZi"}],"key":"RAgc5b1sw9"}],"key":"v9FoVOxlOi"},{"type":"listItem","spread":true,"position":{"start":{"line":18,"column":1},"end":{"line":18,"column":1}},"children":[{"type":"paragraph","children":[{"type":"text","value":"✅ ","position":{"start":{"line":18,"column":1},"end":{"line":18,"column":1}},"key":"pK4JBdM6uM"},{"type":"strong","position":{"start":{"line":18,"column":1},"end":{"line":18,"column":1}},"children":[{"type":"text","value":"Version-controlled infrastructure:","position":{"start":{"line":18,"column":1},"end":{"line":18,"column":1}},"key":"hJBk05afAd"}],"key":"kuo1u3YjSN"},{"type":"text","value":" Save your setup commands in a Git repository.","position":{"start":{"line":18,"column":1},"end":{"line":18,"column":1}},"key":"EzeqmTNRUu"}],"key":"nL6nDyZxBt"}],"key":"iAXIiqdg98"},{"type":"listItem","spread":true,"position":{"start":{"line":19,"column":1},"end":{"line":20,"column":1}},"children":[{"type":"paragraph","children":[{"type":"text","value":"✅ ","position":{"start":{"line":19,"column":1},"end":{"line":19,"column":1}},"key":"n1GuZjJgKr"},{"type":"strong","position":{"start":{"line":19,"column":1},"end":{"line":19,"column":1}},"children":[{"type":"text","value":"Integration with other tools:","position":{"start":{"line":19,"column":1},"end":{"line":19,"column":1}},"key":"JPcGDVCV5o"}],"key":"Akh7uhnyyZ"},{"type":"text","value":" Easily connect your cloud resources with Python scripts, CI/CD pipelines, or Git.","position":{"start":{"line":19,"column":1},"end":{"line":19,"column":1}},"key":"gbEMyd1eui"}],"key":"qSmKh7gUYW"}],"key":"PYAIBdVqPc"}],"key":"eZUQjSUmkX"},{"type":"admonition","kind":"note","children":[{"type":"admonitionTitle","children":[{"type":"text","value":"Note","key":"sGnDNh42cX"}],"key":"uBABng9tGh"},{"type":"paragraph","position":{"start":{"line":22,"column":1},"end":{"line":22,"column":1}},"children":[{"type":"text","value":"Using the console might, however, be more intuitive for beginners or more efficient for one-off tasks, such as learning and exploring GCP, quickly checking a single billing report, creating a single virtual machine instance, creating a single storage bucket, debugging and troubleshooting, etc.","position":{"start":{"line":22,"column":1},"end":{"line":22,"column":1}},"key":"rFwvJ91VFd"}],"key":"mQOBU78Ajb"}],"key":"VZcmpujyra"},{"type":"heading","depth":2,"position":{"start":{"line":25,"column":1},"end":{"line":25,"column":1}},"children":[{"type":"text","value":"Where to Use It?","position":{"start":{"line":25,"column":1},"end":{"line":25,"column":1}},"key":"SG9qhBg4Zj"}],"identifier":"where-to-use-it","label":"Where to Use It?","html_id":"where-to-use-it","implicit":true,"key":"ArJApLuTZQ"},{"type":"list","ordered":true,"start":1,"spread":false,"position":{"start":{"line":27,"column":1},"end":{"line":29,"column":1}},"children":[{"type":"listItem","spread":true,"position":{"start":{"line":27,"column":1},"end":{"line":27,"column":1}},"children":[{"type":"paragraph","children":[{"type":"strong","position":{"start":{"line":27,"column":1},"end":{"line":27,"column":1}},"children":[{"type":"text","value":"Cloud Shell:","position":{"start":{"line":27,"column":1},"end":{"line":27,"column":1}},"key":"QSKIpSK7eV"}],"key":"qnQ6hbGAyx"},{"type":"text","value":" The ","position":{"start":{"line":27,"column":1},"end":{"line":27,"column":1}},"key":"roIMPNRlYT"},{"type":"inlineCode","value":"gcloud","position":{"start":{"line":27,"column":1},"end":{"line":27,"column":1}},"key":"mVhxfb8WXC"},{"type":"text","value":" tool is pre-installed and authenticated in the browser-based Cloud Shell terminal we explored in the previous chapter. No installation required.","position":{"start":{"line":27,"column":1},"end":{"line":27,"column":1}},"key":"PNQ1r6vmUm"}],"key":"Y4vuKYVCaL"}],"key":"dZUlDVsfsv"},{"type":"listItem","spread":true,"position":{"start":{"line":28,"column":1},"end":{"line":29,"column":1}},"children":[{"type":"paragraph","children":[{"type":"strong","position":{"start":{"line":28,"column":1},"end":{"line":28,"column":1}},"children":[{"type":"text","value":"Local Machine:","position":{"start":{"line":28,"column":1},"end":{"line":28,"column":1}},"key":"y7Den1eVuZ"}],"key":"j9wHV8hzX8"},{"type":"text","value":" You can install the Google Cloud SDK on your own laptop (Windows, macOS, or Linux) to manage your cloud projects without opening a browser.","position":{"start":{"line":28,"column":1},"end":{"line":28,"column":1}},"key":"LI3ylM2Pq5"}],"key":"Vols2Vaypt"}],"key":"kQH0g30smn"}],"key":"nhLLhiWul4"},{"type":"heading","depth":2,"position":{"start":{"line":30,"column":1},"end":{"line":30,"column":1}},"children":[{"type":"text","value":"Key Capabilities","position":{"start":{"line":30,"column":1},"end":{"line":30,"column":1}},"key":"KV1I8Y1YPf"}],"identifier":"key-capabilities","label":"Key Capabilities","html_id":"key-capabilities","implicit":true,"key":"S97PTYuxco"},{"type":"list","ordered":false,"spread":false,"position":{"start":{"line":32,"column":1},"end":{"line":38,"column":1}},"children":[{"type":"listItem","spread":true,"position":{"start":{"line":32,"column":1},"end":{"line":32,"column":1}},"children":[{"type":"paragraph","children":[{"type":"strong","position":{"start":{"line":32,"column":1},"end":{"line":32,"column":1}},"children":[{"type":"text","value":"Manage resources","position":{"start":{"line":32,"column":1},"end":{"line":32,"column":1}},"key":"vByxqLixaw"}],"key":"x5Rlc8vKNq"},{"type":"text","value":": Create, modify, delete resources like VMs, storage, and networks.","position":{"start":{"line":32,"column":1},"end":{"line":32,"column":1}},"key":"qyeyHpquoN"}],"key":"OtLrjxPxMW"}],"key":"N7Nr2ttGJO"},{"type":"listItem","spread":true,"position":{"start":{"line":33,"column":1},"end":{"line":33,"column":1}},"children":[{"type":"paragraph","children":[{"type":"strong","position":{"start":{"line":33,"column":1},"end":{"line":33,"column":1}},"children":[{"type":"text","value":"Configure projects","position":{"start":{"line":33,"column":1},"end":{"line":33,"column":1}},"key":"jGX4pn764z"}],"key":"u4dG6z4rcf"},{"type":"text","value":": Quickly switch between projects or set a default project, region, and zone.","position":{"start":{"line":33,"column":1},"end":{"line":33,"column":1}},"key":"AdGYKgSLrb"}],"key":"xocvvO9fiE"}],"key":"ZEFWARoqvg"},{"type":"listItem","spread":true,"position":{"start":{"line":34,"column":1},"end":{"line":34,"column":1}},"children":[{"type":"paragraph","children":[{"type":"strong","position":{"start":{"line":34,"column":1},"end":{"line":34,"column":1}},"children":[{"type":"text","value":"Authenticate","position":{"start":{"line":34,"column":1},"end":{"line":34,"column":1}},"key":"e4D3koYrxs"}],"key":"zfadl9g1uL"},{"type":"text","value":": Log in and manage credentials for yourself or for Service Accounts.","position":{"start":{"line":34,"column":1},"end":{"line":34,"column":1}},"key":"gnyXfvOVDM"}],"key":"znlq2jaqTv"}],"key":"IY9RdPheNn"},{"type":"listItem","spread":true,"position":{"start":{"line":35,"column":1},"end":{"line":35,"column":1}},"children":[{"type":"paragraph","children":[{"type":"strong","position":{"start":{"line":35,"column":1},"end":{"line":35,"column":1}},"children":[{"type":"text","value":"Automate workflows","position":{"start":{"line":35,"column":1},"end":{"line":35,"column":1}},"key":"bcomjacvx0"}],"key":"mpYRaVrDAe"},{"type":"text","value":": Write Bash or Python scripts to automate repetitive cloud infrastructure tasks.","position":{"start":{"line":35,"column":1},"end":{"line":35,"column":1}},"key":"wQljpeFHc8"}],"key":"WCRN8bVuxf"}],"key":"kNLYJXLV1o"},{"type":"listItem","spread":true,"position":{"start":{"line":36,"column":1},"end":{"line":36,"column":1}},"children":[{"type":"paragraph","children":[{"type":"strong","position":{"start":{"line":36,"column":1},"end":{"line":36,"column":1}},"children":[{"type":"text","value":"Query resources","position":{"start":{"line":36,"column":1},"end":{"line":36,"column":1}},"key":"pHKITA4qgo"}],"key":"tw9X5eqrR7"},{"type":"text","value":": List and filter resources (e.g., “Find all VMs that are currently stopped”) and format the output as JSON, YAML, or a table.","position":{"start":{"line":36,"column":1},"end":{"line":36,"column":1}},"key":"mJLzQvnazh"}],"key":"tkhEoO6zMW"}],"key":"D8680MQcxB"},{"type":"listItem","spread":true,"position":{"start":{"line":37,"column":1},"end":{"line":38,"column":1}},"children":[{"type":"paragraph","children":[{"type":"strong","position":{"start":{"line":37,"column":1},"end":{"line":37,"column":1}},"children":[{"type":"text","value":"Control permissions","position":{"start":{"line":37,"column":1},"end":{"line":37,"column":1}},"key":"wA75Ou9aQY"}],"key":"qlpG8bdzPs"},{"type":"text","value":": Manage IAM roles and policies to decide who has access to what.","position":{"start":{"line":37,"column":1},"end":{"line":37,"column":1}},"key":"tuANxZ7OTp"}],"key":"JBLU8A3SBK"}],"key":"X9tTglqN4q"}],"key":"FzlH0k78TL"},{"type":"heading","depth":2,"position":{"start":{"line":39,"column":1},"end":{"line":39,"column":1}},"children":[{"type":"text","value":"Anatomy of a ","position":{"start":{"line":39,"column":1},"end":{"line":39,"column":1}},"key":"Xk0xfJ0Q7G"},{"type":"inlineCode","value":"gcloud","position":{"start":{"line":39,"column":1},"end":{"line":39,"column":1}},"key":"cvLsOEZCNU"},{"type":"text","value":" Command","position":{"start":{"line":39,"column":1},"end":{"line":39,"column":1}},"key":"HWP4H1vZrf"}],"identifier":"anatomy-of-a-gcloud-command","label":"Anatomy of a gcloud Command","html_id":"anatomy-of-a-gcloud-command","implicit":true,"key":"iE2I4wGJ2l"},{"type":"paragraph","position":{"start":{"line":41,"column":1},"end":{"line":41,"column":1}},"children":[{"type":"text","value":"Most commands follow a simple structure:","position":{"start":{"line":41,"column":1},"end":{"line":41,"column":1}},"key":"NRK0i4fru4"}],"key":"nHx6lPWLLs"},{"type":"code","lang":"bash","value":"gcloud [GROUP] [SUBGROUP] [ACTION] [NAME] --[FLAGS]","key":"LiZgiBe73a"},{"type":"list","ordered":false,"spread":false,"position":{"start":{"line":46,"column":1},"end":{"line":52,"column":1}},"children":[{"type":"listItem","spread":true,"position":{"start":{"line":46,"column":1},"end":{"line":46,"column":1}},"children":[{"type":"paragraph","children":[{"type":"inlineCode","value":"gcloud","position":{"start":{"line":46,"column":1},"end":{"line":46,"column":1}},"key":"IiA5wCK7il"},{"type":"text","value":": The base command that calls the Google Cloud SDK.","position":{"start":{"line":46,"column":1},"end":{"line":46,"column":1}},"key":"X5vi3idhuB"}],"key":"SlSVl8DALW"}],"key":"vT7nzsDngT"},{"type":"listItem","spread":true,"position":{"start":{"line":47,"column":1},"end":{"line":47,"column":1}},"children":[{"type":"paragraph","children":[{"type":"inlineCode","value":"[GROUP]","position":{"start":{"line":47,"column":1},"end":{"line":47,"column":1}},"key":"xXzrwjEHks"},{"type":"text","value":": The broad service or resource category you are targeting (e.g., ","position":{"start":{"line":47,"column":1},"end":{"line":47,"column":1}},"key":"QNhNRKM9Rf"},{"type":"inlineCode","value":"compute","position":{"start":{"line":47,"column":1},"end":{"line":47,"column":1}},"key":"XLvvRYSqkM"},{"type":"text","value":", ","position":{"start":{"line":47,"column":1},"end":{"line":47,"column":1}},"key":"OYRghaMhjb"},{"type":"inlineCode","value":"storage","position":{"start":{"line":47,"column":1},"end":{"line":47,"column":1}},"key":"I85JxdEogv"},{"type":"text","value":", ","position":{"start":{"line":47,"column":1},"end":{"line":47,"column":1}},"key":"Fqnvv89Zhw"},{"type":"inlineCode","value":"auth","position":{"start":{"line":47,"column":1},"end":{"line":47,"column":1}},"key":"GRPM5Q0tDe"},{"type":"text","value":", ","position":{"start":{"line":47,"column":1},"end":{"line":47,"column":1}},"key":"PQxTgnPJlT"},{"type":"inlineCode","value":"projects","position":{"start":{"line":47,"column":1},"end":{"line":47,"column":1}},"key":"tphgCpIXlk"},{"type":"text","value":").","position":{"start":{"line":47,"column":1},"end":{"line":47,"column":1}},"key":"tfZdRwLr3t"}],"key":"NrORCCGZVd"}],"key":"EYDHoOo0JX"},{"type":"listItem","spread":true,"position":{"start":{"line":48,"column":1},"end":{"line":48,"column":1}},"children":[{"type":"paragraph","children":[{"type":"inlineCode","value":"[SUBGROUP]","position":{"start":{"line":48,"column":1},"end":{"line":48,"column":1}},"key":"zR6fxJNUSu"},{"type":"text","value":": (Optional) A specific type of resource within that group. For example, under ","position":{"start":{"line":48,"column":1},"end":{"line":48,"column":1}},"key":"XuuZSQIWRx"},{"type":"inlineCode","value":"compute","position":{"start":{"line":48,"column":1},"end":{"line":48,"column":1}},"key":"cEwWduAQMl"},{"type":"text","value":" group, you might target ","position":{"start":{"line":48,"column":1},"end":{"line":48,"column":1}},"key":"nUxDXhgSIP"},{"type":"inlineCode","value":"instances","position":{"start":{"line":48,"column":1},"end":{"line":48,"column":1}},"key":"fZDTfEDGaj"},{"type":"text","value":", ","position":{"start":{"line":48,"column":1},"end":{"line":48,"column":1}},"key":"zOXmeIjdHM"},{"type":"inlineCode","value":"disks","position":{"start":{"line":48,"column":1},"end":{"line":48,"column":1}},"key":"L0c46nrDeF"},{"type":"text","value":", or ","position":{"start":{"line":48,"column":1},"end":{"line":48,"column":1}},"key":"eC46u1gi0l"},{"type":"inlineCode","value":"networks","position":{"start":{"line":48,"column":1},"end":{"line":48,"column":1}},"key":"WY9bYpRafn"},{"type":"text","value":".","position":{"start":{"line":48,"column":1},"end":{"line":48,"column":1}},"key":"O8B5P9PyO4"}],"key":"lERGfaMTBn"}],"key":"pzWN7bN1ho"},{"type":"listItem","spread":true,"position":{"start":{"line":49,"column":1},"end":{"line":49,"column":1}},"children":[{"type":"paragraph","children":[{"type":"inlineCode","value":"[ACTION]","position":{"start":{"line":49,"column":1},"end":{"line":49,"column":1}},"key":"omLBIOwePm"},{"type":"text","value":": The “verb” or what you want to do to the resource (e.g., ","position":{"start":{"line":49,"column":1},"end":{"line":49,"column":1}},"key":"KzCwtuvDii"},{"type":"inlineCode","value":"create","position":{"start":{"line":49,"column":1},"end":{"line":49,"column":1}},"key":"LrMMBH6cXu"},{"type":"text","value":", ","position":{"start":{"line":49,"column":1},"end":{"line":49,"column":1}},"key":"Iy918Nwjuw"},{"type":"inlineCode","value":"list","position":{"start":{"line":49,"column":1},"end":{"line":49,"column":1}},"key":"IMHP4uXZMy"},{"type":"text","value":", ","position":{"start":{"line":49,"column":1},"end":{"line":49,"column":1}},"key":"y5OoHBjvS0"},{"type":"inlineCode","value":"delete","position":{"start":{"line":49,"column":1},"end":{"line":49,"column":1}},"key":"JS1wihuYA5"},{"type":"text","value":", ","position":{"start":{"line":49,"column":1},"end":{"line":49,"column":1}},"key":"ZHb7qCaazd"},{"type":"inlineCode","value":"describe","position":{"start":{"line":49,"column":1},"end":{"line":49,"column":1}},"key":"bMnzwv40H7"},{"type":"text","value":", ","position":{"start":{"line":49,"column":1},"end":{"line":49,"column":1}},"key":"GN1aMaGhzg"},{"type":"inlineCode","value":"stop","position":{"start":{"line":49,"column":1},"end":{"line":49,"column":1}},"key":"aplyE4zfwQ"},{"type":"text","value":").","position":{"start":{"line":49,"column":1},"end":{"line":49,"column":1}},"key":"eNL6KUioT9"}],"key":"wSYjb7jpei"}],"key":"M5qYMsmcCJ"},{"type":"listItem","spread":true,"position":{"start":{"line":50,"column":1},"end":{"line":50,"column":1}},"children":[{"type":"paragraph","children":[{"type":"inlineCode","value":"[NAME]","position":{"start":{"line":50,"column":1},"end":{"line":50,"column":1}},"key":"PUWLChFNOv"},{"type":"text","value":": The specific identity of the resource you are acting upon (e.g., the name of your VM instance).","position":{"start":{"line":50,"column":1},"end":{"line":50,"column":1}},"key":"kw5wURv8zt"}],"key":"XkkdegdogN"}],"key":"TMDFLWvCvh"},{"type":"listItem","spread":true,"position":{"start":{"line":51,"column":1},"end":{"line":52,"column":1}},"children":[{"type":"paragraph","children":[{"type":"inlineCode","value":"--[FLAGS]","position":{"start":{"line":51,"column":1},"end":{"line":51,"column":1}},"key":"uw3L4WNVVA"},{"type":"text","value":": Optional parameters that modify the command, usually starting with double dashes. These specify details like ","position":{"start":{"line":51,"column":1},"end":{"line":51,"column":1}},"key":"GvKxEaBDff"},{"type":"inlineCode","value":"--zone","position":{"start":{"line":51,"column":1},"end":{"line":51,"column":1}},"key":"Jitr1YA2lt"},{"type":"text","value":", ","position":{"start":{"line":51,"column":1},"end":{"line":51,"column":1}},"key":"tGDKrvBrhD"},{"type":"inlineCode","value":"--machine-type","position":{"start":{"line":51,"column":1},"end":{"line":51,"column":1}},"key":"oln6ArwEUQ"},{"type":"text","value":", or ","position":{"start":{"line":51,"column":1},"end":{"line":51,"column":1}},"key":"mwmLwEkTDm"},{"type":"inlineCode","value":"--format","position":{"start":{"line":51,"column":1},"end":{"line":51,"column":1}},"key":"aWGMAbkcmR"},{"type":"text","value":".","position":{"start":{"line":51,"column":1},"end":{"line":51,"column":1}},"key":"fIbT7mBKpS"}],"key":"h5zmN8MhR4"}],"key":"zqzNRtIVXt"}],"key":"auVZhQ9pek"},{"type":"heading","depth":3,"position":{"start":{"line":53,"column":1},"end":{"line":53,"column":1}},"children":[{"type":"text","value":"Example in Action","position":{"start":{"line":53,"column":1},"end":{"line":53,"column":1}},"key":"Soxvzvee9p"}],"identifier":"example-in-action","label":"Example in Action","html_id":"example-in-action","implicit":true,"key":"OZ4KGe015a"},{"type":"paragraph","position":{"start":{"line":55,"column":1},"end":{"line":55,"column":1}},"children":[{"type":"text","value":"If you want to create a virtual machine, the command looks like this:","position":{"start":{"line":55,"column":1},"end":{"line":55,"column":1}},"key":"avLJh9qTAM"}],"key":"zCBRbPIuBF"},{"type":"table","position":{"start":{"line":57,"column":1},"end":{"line":63,"column":1}},"children":[{"type":"tableRow","position":{"start":{"line":57,"column":1},"end":{"line":57,"column":1}},"children":[{"type":"tableCell","header":true,"position":{"start":{"line":57,"column":1},"end":{"line":57,"column":1}},"children":[{"type":"text","value":"Part","position":{"start":{"line":57,"column":1},"end":{"line":57,"column":1}},"key":"RoWMXMDpua"}],"key":"aiTqFmjAqA"},{"type":"tableCell","header":true,"position":{"start":{"line":57,"column":1},"end":{"line":57,"column":1}},"children":[{"type":"text","value":"Command Fragment","position":{"start":{"line":57,"column":1},"end":{"line":57,"column":1}},"key":"M1Um0GXVY4"}],"key":"NgQWS4zq65"},{"type":"tableCell","header":true,"position":{"start":{"line":57,"column":1},"end":{"line":57,"column":1}},"children":[{"type":"text","value":"Purpose","position":{"start":{"line":57,"column":1},"end":{"line":57,"column":1}},"key":"rbP0z9G31a"}],"key":"HW0Y0EPrRf"}],"key":"LcJQpYoiiG"},{"type":"tableRow","position":{"start":{"line":59,"column":1},"end":{"line":59,"column":1}},"children":[{"type":"tableCell","position":{"start":{"line":59,"column":1},"end":{"line":59,"column":1}},"children":[{"type":"text","value":"Group","position":{"start":{"line":59,"column":1},"end":{"line":59,"column":1}},"key":"lsCm44uETV"}],"key":"DPs3C40d9h"},{"type":"tableCell","position":{"start":{"line":59,"column":1},"end":{"line":59,"column":1}},"children":[{"type":"inlineCode","value":"compute","position":{"start":{"line":59,"column":1},"end":{"line":59,"column":1}},"key":"aTAxVBZsiD"}],"key":"F0tRc1HrAe"},{"type":"tableCell","position":{"start":{"line":59,"column":1},"end":{"line":59,"column":1}},"children":[{"type":"text","value":"We are working with the compute engine service","position":{"start":{"line":59,"column":1},"end":{"line":59,"column":1}},"key":"A1fjtsT3fq"}],"key":"cPi8pQWrml"}],"key":"gdwE3bDB8M"},{"type":"tableRow","position":{"start":{"line":60,"column":1},"end":{"line":60,"column":1}},"children":[{"type":"tableCell","position":{"start":{"line":60,"column":1},"end":{"line":60,"column":1}},"children":[{"type":"text","value":"Subgroup","position":{"start":{"line":60,"column":1},"end":{"line":60,"column":1}},"key":"apAISJ5MvD"}],"key":"TmAJGvxlfb"},{"type":"tableCell","position":{"start":{"line":60,"column":1},"end":{"line":60,"column":1}},"children":[{"type":"inlineCode","value":"instances","position":{"start":{"line":60,"column":1},"end":{"line":60,"column":1}},"key":"MoZ5yoBKmj"}],"key":"KIlP7tdz91"},{"type":"tableCell","position":{"start":{"line":60,"column":1},"end":{"line":60,"column":1}},"children":[{"type":"text","value":"Specifically, we want a virtual machine","position":{"start":{"line":60,"column":1},"end":{"line":60,"column":1}},"key":"A6F4z47UVy"}],"key":"ocylWvTzOR"}],"key":"AAaWtjZgl4"},{"type":"tableRow","position":{"start":{"line":61,"column":1},"end":{"line":61,"column":1}},"children":[{"type":"tableCell","position":{"start":{"line":61,"column":1},"end":{"line":61,"column":1}},"children":[{"type":"text","value":"Action","position":{"start":{"line":61,"column":1},"end":{"line":61,"column":1}},"key":"I3r5qDHZDT"}],"key":"YKzlylMkjJ"},{"type":"tableCell","position":{"start":{"line":61,"column":1},"end":{"line":61,"column":1}},"children":[{"type":"inlineCode","value":"create","position":{"start":{"line":61,"column":1},"end":{"line":61,"column":1}},"key":"WPh2Fm7wlQ"}],"key":"QMOytqdtSu"},{"type":"tableCell","position":{"start":{"line":61,"column":1},"end":{"line":61,"column":1}},"children":[{"type":"text","value":"We want to create a new virtual machine instance","position":{"start":{"line":61,"column":1},"end":{"line":61,"column":1}},"key":"tTJHjVJfjB"}],"key":"NxjAWAi5fS"}],"key":"dG4yumDycs"},{"type":"tableRow","position":{"start":{"line":62,"column":1},"end":{"line":62,"column":1}},"children":[{"type":"tableCell","position":{"start":{"line":62,"column":1},"end":{"line":62,"column":1}},"children":[{"type":"text","value":"Name","position":{"start":{"line":62,"column":1},"end":{"line":62,"column":1}},"key":"DuBwQ86MH5"}],"key":"QJXaks5W5S"},{"type":"tableCell","position":{"start":{"line":62,"column":1},"end":{"line":62,"column":1}},"children":[{"type":"inlineCode","value":"aims-vm","position":{"start":{"line":62,"column":1},"end":{"line":62,"column":1}},"key":"sTVXfDpihP"}],"key":"kHCgi8EFiW"},{"type":"tableCell","position":{"start":{"line":62,"column":1},"end":{"line":62,"column":1}},"children":[{"type":"text","value":"This is the name we are giving the instance","position":{"start":{"line":62,"column":1},"end":{"line":62,"column":1}},"key":"rKRnpHnUsE"}],"key":"tURB3utFjm"}],"key":"udwP45RXU8"},{"type":"tableRow","position":{"start":{"line":63,"column":1},"end":{"line":63,"column":1}},"children":[{"type":"tableCell","position":{"start":{"line":63,"column":1},"end":{"line":63,"column":1}},"children":[{"type":"text","value":"Flag","position":{"start":{"line":63,"column":1},"end":{"line":63,"column":1}},"key":"xzquH6mICt"}],"key":"XXaW0hqz4N"},{"type":"tableCell","position":{"start":{"line":63,"column":1},"end":{"line":63,"column":1}},"children":[{"type":"inlineCode","value":"--zone=us-central1-a","position":{"start":{"line":63,"column":1},"end":{"line":63,"column":1}},"key":"qKuAkZcXQo"}],"key":"vY8KKjTawg"},{"type":"tableCell","position":{"start":{"line":63,"column":1},"end":{"line":63,"column":1}},"children":[{"type":"text","value":"This tells GCP what zone to create the instance","position":{"start":{"line":63,"column":1},"end":{"line":63,"column":1}},"key":"qG8iPt6FSI"}],"key":"qqrJgSfsws"}],"key":"ftKGDZxipe"}],"key":"aQxIXzjt2y"},{"type":"paragraph","position":{"start":{"line":65,"column":1},"end":{"line":65,"column":1}},"children":[{"type":"text","value":"The full command is:","position":{"start":{"line":65,"column":1},"end":{"line":65,"column":1}},"key":"tk0zVtUtYQ"}],"key":"LKsXlcl4KR"},{"type":"code","lang":"bash","value":"gcloud compute instances create aims-vm --zone=us-central1-a","key":"dGaPyr333h"},{"type":"thematicBreak","position":{"start":{"line":71,"column":1},"end":{"line":71,"column":1}},"key":"Us85y6zAMb"},{"type":"heading","depth":2,"position":{"start":{"line":73,"column":1},"end":{"line":73,"column":1}},"children":[{"type":"text","value":"🔑 Key Takeaways","position":{"start":{"line":73,"column":1},"end":{"line":73,"column":1}},"key":"l1UBrm56re"}],"identifier":"id-key-takeaways","label":"🔑 Key Takeaways","html_id":"id-key-takeaways","implicit":true,"key":"HNoKml9I4g"},{"type":"list","ordered":false,"spread":false,"position":{"start":{"line":75,"column":1},"end":{"line":78,"column":1}},"children":[{"type":"listItem","spread":true,"position":{"start":{"line":75,"column":1},"end":{"line":75,"column":1}},"children":[{"type":"paragraph","children":[{"type":"text","value":"While the console is great for exploring, the CLI is the superior choice for automating repetitive tasks, batch operations, and creating reproducible environments.","position":{"start":{"line":75,"column":1},"end":{"line":75,"column":1}},"key":"djkWBglJKw"}],"key":"DXjOfsZIL2"}],"key":"LmXKKvnbqe"},{"type":"listItem","spread":true,"position":{"start":{"line":76,"column":1},"end":{"line":76,"column":1}},"children":[{"type":"paragraph","children":[{"type":"text","value":"You don’t need to install anything immediately; the ","position":{"start":{"line":76,"column":1},"end":{"line":76,"column":1}},"key":"IdXbBZVdDE"},{"type":"strong","position":{"start":{"line":76,"column":1},"end":{"line":76,"column":1}},"children":[{"type":"text","value":"Cloud Shell","position":{"start":{"line":76,"column":1},"end":{"line":76,"column":1}},"key":"X1mHme46BY"}],"key":"tvPXNTbuMv"},{"type":"text","value":" provides a fully authenticated, pre-configured ","position":{"start":{"line":76,"column":1},"end":{"line":76,"column":1}},"key":"VlfrEEntwZ"},{"type":"inlineCode","value":"gcloud","position":{"start":{"line":76,"column":1},"end":{"line":76,"column":1}},"key":"gOOTKFmWHK"},{"type":"text","value":" environment directly in your browser.","position":{"start":{"line":76,"column":1},"end":{"line":76,"column":1}},"key":"pY6eIujXQO"}],"key":"TMgPbwKrdS"}],"key":"a46JKke22Y"},{"type":"listItem","spread":true,"position":{"start":{"line":77,"column":1},"end":{"line":78,"column":1}},"children":[{"type":"paragraph","children":[{"type":"text","value":"Every command follows a logical structure with ","position":{"start":{"line":77,"column":1},"end":{"line":77,"column":1}},"key":"xncwY5w6dy"},{"type":"inlineCode","value":"gcloud","position":{"start":{"line":77,"column":1},"end":{"line":77,"column":1}},"key":"uqYjlM116X"},{"type":"text","value":" (the tool), ","position":{"start":{"line":77,"column":1},"end":{"line":77,"column":1}},"key":"ab0B85vcBJ"},{"type":"strong","position":{"start":{"line":77,"column":1},"end":{"line":77,"column":1}},"children":[{"type":"text","value":"Group","position":{"start":{"line":77,"column":1},"end":{"line":77,"column":1}},"key":"HiKdtC9K1Z"}],"key":"HMXHi61pG9"},{"type":"text","value":" (the service), ","position":{"start":{"line":77,"column":1},"end":{"line":77,"column":1}},"key":"vIeOWqSAQd"},{"type":"strong","position":{"start":{"line":77,"column":1},"end":{"line":77,"column":1}},"children":[{"type":"text","value":"Subgroup","position":{"start":{"line":77,"column":1},"end":{"line":77,"column":1}},"key":"hzDpYaEXbp"}],"key":"kzjgvjqnVl"},{"type":"text","value":" (the resource), and ","position":{"start":{"line":77,"column":1},"end":{"line":77,"column":1}},"key":"VdqY5FXovm"},{"type":"strong","position":{"start":{"line":77,"column":1},"end":{"line":77,"column":1}},"children":[{"type":"text","value":"Action","position":{"start":{"line":77,"column":1},"end":{"line":77,"column":1}},"key":"gTpsgcmdhB"}],"key":"IaiSYOHdjC"},{"type":"text","value":" (the verb).","position":{"start":{"line":77,"column":1},"end":{"line":77,"column":1}},"key":"UdzAqyTDN6"}],"key":"kRtO4rkcrY"}],"key":"W9p2M8qed4"}],"key":"x0kqrn12WF"},{"type":"heading","depth":2,"position":{"start":{"line":79,"column":1},"end":{"line":79,"column":1}},"children":[{"type":"text","value":"🚀 What’s Next?","position":{"start":{"line":79,"column":1},"end":{"line":79,"column":1}},"key":"x2mAdzNFTI"}],"identifier":"id-whats-next","label":"🚀 What’s Next?","html_id":"id-whats-next","implicit":true,"key":"OnSFy9lSzr"},{"type":"paragraph","position":{"start":{"line":81,"column":1},"end":{"line":81,"column":1}},"children":[{"type":"text","value":"We are moving into the practical hands-on phase of the GCP foundations part. In the next two chapters, you will complete structured hands-on tutorials:","position":{"start":{"line":81,"column":1},"end":{"line":81,"column":1}},"key":"OBSmAFsuSx"}],"key":"jA5ByzAeFl"},{"type":"paragraph","position":{"start":{"line":83,"column":1},"end":{"line":83,"column":1}},"children":[{"type":"strong","position":{"start":{"line":83,"column":1},"end":{"line":83,"column":1}},"children":[{"type":"text","value":"Hands-on Tutorial 1: Using the Console","position":{"start":{"line":83,"column":1},"end":{"line":83,"column":1}},"key":"OXNVTnytse"}],"key":"vT9tk977FH"}],"key":"baWzrYPlY1"},{"type":"list","ordered":false,"spread":false,"position":{"start":{"line":84,"column":1},"end":{"line":86,"column":1}},"children":[{"type":"listItem","spread":true,"position":{"start":{"line":84,"column":1},"end":{"line":84,"column":1}},"children":[{"type":"paragraph","children":[{"type":"strong","position":{"start":{"line":84,"column":1},"end":{"line":84,"column":1}},"children":[{"type":"text","value":"Create a VM","position":{"start":{"line":84,"column":1},"end":{"line":84,"column":1}},"key":"foddLI2jj8"}],"key":"wFBNlL6SgL"},{"type":"text","value":": Manually configure and launch a virtual machine using the Compute Engine dashboard.","position":{"start":{"line":84,"column":1},"end":{"line":84,"column":1}},"key":"dJWK6j748e"}],"key":"V9yEtMJGxs"}],"key":"y50esSgTSF"},{"type":"listItem","spread":true,"position":{"start":{"line":85,"column":1},"end":{"line":86,"column":1}},"children":[{"type":"paragraph","children":[{"type":"strong","position":{"start":{"line":85,"column":1},"end":{"line":85,"column":1}},"children":[{"type":"text","value":"Browser-based SSH","position":{"start":{"line":85,"column":1},"end":{"line":85,"column":1}},"key":"qDqHHo80sS"}],"key":"Pe1Yhqo1Vq"},{"type":"text","value":": Connect to your instance directly through the Google Cloud console.","position":{"start":{"line":85,"column":1},"end":{"line":85,"column":1}},"key":"Xs62eoGWcO"}],"key":"sJrJhHZoyc"}],"key":"jvAdkyGgCj"}],"key":"wNRtCeKeIJ"},{"type":"paragraph","position":{"start":{"line":87,"column":1},"end":{"line":87,"column":1}},"children":[{"type":"strong","position":{"start":{"line":87,"column":1},"end":{"line":87,"column":1}},"children":[{"type":"text","value":"Hands-on Tutorial 2: Using the ","position":{"start":{"line":87,"column":1},"end":{"line":87,"column":1}},"key":"VwQV4x7M8Y"},{"type":"inlineCode","value":"gcloud","position":{"start":{"line":87,"column":1},"end":{"line":87,"column":1}},"key":"q52GVo71z1"},{"type":"text","value":" CLI","position":{"start":{"line":87,"column":1},"end":{"line":87,"column":1}},"key":"PVZtlwV0M6"}],"key":"RJXD6N5wMD"}],"key":"giYMofvLir"},{"type":"list","ordered":false,"spread":false,"position":{"start":{"line":88,"column":1},"end":{"line":91,"column":1}},"children":[{"type":"listItem","spread":true,"position":{"start":{"line":88,"column":1},"end":{"line":88,"column":1}},"children":[{"type":"paragraph","children":[{"type":"strong","position":{"start":{"line":88,"column":1},"end":{"line":88,"column":1}},"children":[{"type":"text","value":"Local Setup","position":{"start":{"line":88,"column":1},"end":{"line":88,"column":1}},"key":"RNaAEIvvGk"}],"key":"S1XOfEKFLb"},{"type":"text","value":": Install and initialize the Google Cloud SDK on your own computer.","position":{"start":{"line":88,"column":1},"end":{"line":88,"column":1}},"key":"cgeOVs3mu7"}],"key":"r7dfI6iutf"}],"key":"yL7UzByg6y"},{"type":"listItem","spread":true,"position":{"start":{"line":89,"column":1},"end":{"line":89,"column":1}},"children":[{"type":"paragraph","children":[{"type":"strong","position":{"start":{"line":89,"column":1},"end":{"line":89,"column":1}},"children":[{"type":"text","value":"Automation","position":{"start":{"line":89,"column":1},"end":{"line":89,"column":1}},"key":"G2MhEifWOz"}],"key":"pEZ9sDwqBJ"},{"type":"text","value":": Use ","position":{"start":{"line":89,"column":1},"end":{"line":89,"column":1}},"key":"T18uWPnyF5"},{"type":"inlineCode","value":"gcloud","position":{"start":{"line":89,"column":1},"end":{"line":89,"column":1}},"key":"LtdUWr653a"},{"type":"text","value":" to create VMs, manage SSH keys from the terminal, and set up a Python environment.","position":{"start":{"line":89,"column":1},"end":{"line":89,"column":1}},"key":"u0nQxSOq8y"}],"key":"B1sZiKR2N6"}],"key":"e8jb1TBBLh"},{"type":"listItem","spread":true,"position":{"start":{"line":90,"column":1},"end":{"line":91,"column":1}},"children":[{"type":"paragraph","children":[{"type":"strong","position":{"start":{"line":90,"column":1},"end":{"line":90,"column":1}},"children":[{"type":"text","value":"Scripting","position":{"start":{"line":90,"column":1},"end":{"line":90,"column":1}},"key":"m5EMKH9fON"}],"key":"hDPeC4slKD"},{"type":"text","value":": Write Bash scripts to create and stop multiple VMs at once to manage your credits efficiently.","position":{"start":{"line":90,"column":1},"end":{"line":90,"column":1}},"key":"Qe56a3jzpX"}],"key":"XKuK3YbYDj"}],"key":"ITznonQLJI"}],"key":"aXqREkyjhI"},{"type":"thematicBreak","position":{"start":{"line":92,"column":1},"end":{"line":92,"column":1}},"key":"c447vYUNDo"},{"type":"heading","depth":2,"position":{"start":{"line":94,"column":1},"end":{"line":94,"column":1}},"children":[{"type":"text","value":"📚 References & Further Reading","position":{"start":{"line":94,"column":1},"end":{"line":94,"column":1}},"key":"XPhhWswyvi"}],"identifier":"id-references-further-reading","label":"📚 References & Further Reading","html_id":"id-references-further-reading","implicit":true,"key":"G3KpMpim5h"},{"type":"list","ordered":false,"spread":false,"position":{"start":{"line":96,"column":1},"end":{"line":104,"column":1}},"children":[{"type":"listItem","spread":true,"position":{"start":{"line":96,"column":1},"end":{"line":96,"column":1}},"children":[{"type":"paragraph","children":[{"type":"link","url":"https://docs.cloud.google.com/sdk/gcloud","position":{"start":{"line":96,"column":1},"end":{"line":96,"column":1}},"children":[{"type":"text","value":"gcloud CLI Overview","position":{"start":{"line":96,"column":1},"end":{"line":96,"column":1}},"key":"xE3xhbi7PR"}],"urlSource":"https://docs.cloud.google.com/sdk/gcloud","key":"gvfHYT5Oje"},{"type":"text","value":" - The official documentation. A great starting point.","position":{"start":{"line":96,"column":1},"end":{"line":96,"column":1}},"key":"vUrSzgxfmd"}],"key":"QssByzUfFZ"}],"key":"lMfj9msTz5"},{"type":"listItem","spread":true,"position":{"start":{"line":97,"column":1},"end":{"line":97,"column":1}},"children":[{"type":"paragraph","children":[{"type":"link","url":"https://docs.cloud.google.com/sdk/docs/cheatsheet","position":{"start":{"line":97,"column":1},"end":{"line":97,"column":1}},"children":[{"type":"text","value":"gcloud CLI Cheat Sheet","position":{"start":{"line":97,"column":1},"end":{"line":97,"column":1}},"key":"lAF9pA2yer"}],"urlSource":"https://docs.cloud.google.com/sdk/docs/cheatsheet","key":"BZ2u2xnQHP"},{"type":"text","value":" - A high-value reference for the most common commands.","position":{"start":{"line":97,"column":1},"end":{"line":97,"column":1}},"key":"I2Hxb67yg7"}],"key":"UfONZEKChq"}],"key":"agPyQ7oNDs"},{"type":"listItem","spread":true,"position":{"start":{"line":98,"column":1},"end":{"line":98,"column":1}},"children":[{"type":"paragraph","children":[{"type":"link","url":"https://docs.cloud.google.com/shell/docs","position":{"start":{"line":98,"column":1},"end":{"line":98,"column":1}},"children":[{"type":"text","value":"Cloud Shell Guide","position":{"start":{"line":98,"column":1},"end":{"line":98,"column":1}},"key":"iLcI3i60hu"}],"urlSource":"https://docs.cloud.google.com/shell/docs","key":"tHWcbuoq1L"},{"type":"text","value":" - Deeper details on the browser-based terminal.","position":{"start":{"line":98,"column":1},"end":{"line":98,"column":1}},"key":"J1Yh1YUx8y"}],"key":"K3wzCbvgtM"}],"key":"AkXMfISDip"},{"type":"listItem","spread":true,"position":{"start":{"line":99,"column":1},"end":{"line":104,"column":1}},"children":[{"type":"paragraph","children":[{"type":"link","url":"https://docs.cloud.google.com/sdk/docs/install-sdk","position":{"start":{"line":99,"column":1},"end":{"line":99,"column":1}},"children":[{"type":"text","value":"SDK Installation Steps","position":{"start":{"line":99,"column":1},"end":{"line":99,"column":1}},"key":"KZzA4d8nsi"}],"urlSource":"https://docs.cloud.google.com/sdk/docs/install-sdk","key":"JC4KrVgiME"},{"type":"text","value":" - Official guides for Windows, macOS, and Linux.","position":{"start":{"line":99,"column":1},"end":{"line":99,"column":1}},"key":"TtYi6G2zwc"}],"key":"npiN3zxsew"}],"key":"e9Lq1Hp0n8"}],"key":"yw7KYkZk1n"}],"key":"DvqGMAQKGD"}],"key":"sDxiyOiArl"},"references":{"cite":{"order":[],"data":{}}},"footer":{"navigation":{"prev":{"title":"The GCP Console","url":"/part1-gcp-foundations/gcp-console","group":"Part 1 - GCP Foundations"},"next":{"title":"Hands-On 01: Create a VM via GCP Console","url":"/part1-gcp-foundations/hands-on-gcp-console","group":"Part 1 - GCP Foundations"}}},"domain":"http://localhost:3000"}